conflspserver/__init__.py
conflspserver/__main__.py
conflspserver/server.py
conflspserver/test.py
conflspserver/cst/__init__.py
conflspserver/cst/code_completion_core.py
conflspserver/cst/diagnostic_listener.py
conflspserver/cst/symbol_table_visitor.py
conflspserver/cst/symbol_table_visitor_dcl.py
conflspserver/filewriter/__init__.py
conflspserver/filewriter/code_generator.py
conflspserver/filewriter/jinja-templates/__init__.py
conflspserver/filewriter/jinja-templates/mitgcm/__init__.py
conflspserver/filewriter/jinja-templates/uvic/__init__.py
conflspserver/gen/python/Configuration/ConfigurationLexer.py
conflspserver/gen/python/Configuration/ConfigurationListener.py
conflspserver/gen/python/Configuration/ConfigurationParser.py
conflspserver/gen/python/Configuration/ConfigurationVisitor.py
conflspserver/gen/python/Declaration/DeclarationLexer.py
conflspserver/gen/python/Declaration/DeclarationListener.py
conflspserver/gen/python/Declaration/DeclarationParser.py
conflspserver/gen/python/Declaration/DeclarationVisitor.py
conflspserver/symboltable/__init__.py
conflspserver/symboltable/symbol_table.py
conflspserver/utils/__init__.py
conflspserver/utils/calc.py
conflspserver/utils/compute_token_index.py
conflspserver/utils/conf_errors_strategy.py
conflspserver/utils/suggest_variables.py
dcllspserver/__init__.py
dcllspserver/__main__.py
dcllspserver/server.py
dcllspserver/test.py
dcllspserver/cst/__init__.py
dcllspserver/cst/code_completion_core.py
dcllspserver/cst/diagnostic_listener.py
dcllspserver/cst/symbol_table_visitor_dcl.py
dcllspserver/filewriter/__init__.py
dcllspserver/filewriter/jinja-templates/__init__.py
dcllspserver/gen/python/BgcDsl/BgcDslLexer.py
dcllspserver/gen/python/BgcDsl/BgcDslListener.py
dcllspserver/gen/python/BgcDsl/BgcDslParser.py
dcllspserver/gen/python/BgcDsl/BgcDslVisitor.py
dcllspserver/gen/python/Configuration/ConfigurationLexer.py
dcllspserver/gen/python/Configuration/ConfigurationListener.py
CPDSL_Language_Server-0.40.0.dist-info/LICENSE.txt
CPDSL_Language_Server-0.40.0.dist-info/METADATA
CPDSL_Language_Server-0.40.0.dist-info/WHEEL
CPDSL_Language_Server-0.40.0.dist-info/entry_points.txt
CPDSL_Language_Server-0.40.0.dist-info/top_level.txt
CPDSL_Language_Server-0.40.0.dist-info/RECORD
